{
    "Ar36": {
        "error": 0.0002969855642491671, 
        "fit": "Parabolic", 
        "value": 0.007945740636196252
    }, 
    "Ar37": {
        "error": 0.01409390730788535, 
        "fit": "linear", 
        "value": -0.13120967720827464
    }, 
    "Ar38": {
        "error": 0.014258266238412162, 
        "fit": "linear", 
        "value": 0.05200317981394792
    }, 
    "Ar39": {
        "error": 0.02764381522303222, 
        "fit": "Parabolic", 
        "value": 13.04394577531441
    }, 
    "Ar40": {
        "error": 0.03797788513372562, 
        "fit": "Parabolic", 
        "value": 188.68409412818056
    }
}