{
    "Ar40AX": {
        "error": 0.007420650583017045, 
        "fit": "previous", 
        "references": [
            {
                "exclude": false, 
                "record_id": "bc-02-J-647"
            }
        ], 
        "value": 3.8911316413989128
    }, 
    "Ar40H1": {
        "error": 0.007420650583017045, 
        "fit": "previous", 
        "references": [
            {
                "exclude": false, 
                "record_id": "bc-02-J-647"
            }
        ], 
        "value": 3.8911316413989128
    }, 
    "Ar40L2": {
        "error": 0.007420650583017045, 
        "fit": "previous", 
        "references": [
            {
                "exclude": false, 
                "record_id": "bc-02-J-647"
            }
        ], 
        "value": 3.8911316413989128
    }
}