{
    "Ar36": {
        "error": 0.00018845037862652136, 
        "fit": "previous", 
        "references": [
            {
                "exclude": false, 
                "record_id": "bc-02-J-893"
            }
        ], 
        "value": 0.003541729824263636
    }, 
    "Ar37": {
        "error": 0.004964367319439926, 
        "fit": "previous", 
        "references": [
            {
                "exclude": false, 
                "record_id": "bc-02-J-893"
            }
        ], 
        "value": 0.051737619933928024
    }, 
    "Ar38": {
        "error": 0.002315953213899685, 
        "fit": "previous", 
        "references": [
            {
                "exclude": false, 
                "record_id": "bc-02-J-893"
            }
        ], 
        "value": -0.0003691600322281059
    }, 
    "Ar39": {
        "error": 0.009853227762002393, 
        "fit": "previous", 
        "references": [
            {
                "exclude": false, 
                "record_id": "bc-02-J-893"
            }
        ], 
        "value": 0.0317539178554503
    }, 
    "Ar40": {
        "error": 0.007694238455317941, 
        "fit": "previous", 
        "references": [
            {
                "exclude": false, 
                "record_id": "bc-02-J-893"
            }
        ], 
        "value": 0.35514752959852536
    }, 
    "Ar41": {
        "error": 0.004435653576158523, 
        "fit": "previous", 
        "references": [
            {
                "exclude": false, 
                "record_id": "bc-02-J-893"
            }
        ], 
        "value": 0.018490644341565207
    }
}