{
    "beam_diameter": "", 
    "cleanup_duration": 0.0, 
    "commit": "63a1adfe58c698ffa15cb724cbb4f9113c186084", 
    "extract_device": "Fusions CO2", 
    "extract_duration": 0.0, 
    "extract_units": "", 
    "extract_value": 0.0, 
    "pattern": "", 
    "positions": [
        {
            "is_degas": false, 
            "position": "", 
            "x": null, 
            "y": null, 
            "z": null
        }
    ], 
    "ramp_duration": 0.0, 
    "ramp_rate": 0.0, 
    "request": "", 
    "response": "", 
    "sblob": "", 
    "tray": "", 
    "weight": 0.0
}