{
    "Ar36": {
        "error": 0.00013691564063350717,
        "fit": "Bracketing Interpolate",
        "references": [
            {
                "exclude": "ok",
                "record_id": "bu-FC-J-8313",
                "uuid": "0c07543a-f9c1-4862-8dc6-07535ac96d6c"
            },
            {
                "exclude": "ok",
                "record_id": "bu-FC-J-8314",
                "uuid": "6ccaa132-9c86-44a7-91ed-c8fdc767d79e"
            },
            {
                "exclude": "ok",
                "record_id": "bu-FC-J-8315",
                "uuid": "cbcbc245-5469-457a-90b3-fe77b7dc6f25"
            },
            {
                "exclude": "ok",
                "record_id": "bu-FC-J-8316",
                "uuid": "c6ecb00f-17c4-4f29-9960-b45c9a79acef"
            },
            {
                "exclude": "ok",
                "record_id": "bu-FC-J-8317",
                "uuid": "89aa7bc2-a562-4a49-84ff-541e939c6152"
            },
            {
                "exclude": "ok",
                "record_id": "bu-FC-J-8318",
                "uuid": "02db119a-44a9-4021-94d9-08939571fd5e"
            },
            {
                "exclude": "ok",
                "record_id": "bu-FC-J-8319",
                "uuid": "65755db4-e347-4b44-91c7-ee830e5e45ec"
            },
            {
                "exclude": "ok",
                "record_id": "bu-FC-J-8320",
                "uuid": "862c27ab-bd5c-4185-9f45-4521eeaed791"
            }
        ],
        "reviewed": true,
        "value": 0.004570888454287264
    },
    "Ar37": {
        "error": 0.0038643233617954346,
        "fit": "Bracketing Interpolate",
        "references": [
            {
                "exclude": "ok",
                "record_id": "bu-FC-J-8313",
                "uuid": "0c07543a-f9c1-4862-8dc6-07535ac96d6c"
            },
            {
                "exclude": "ok",
                "record_id": "bu-FC-J-8314",
                "uuid": "6ccaa132-9c86-44a7-91ed-c8fdc767d79e"
            },
            {
                "exclude": "ok",
                "record_id": "bu-FC-J-8315",
                "uuid": "cbcbc245-5469-457a-90b3-fe77b7dc6f25"
            },
            {
                "exclude": "ok",
                "record_id": "bu-FC-J-8316",
                "uuid": "c6ecb00f-17c4-4f29-9960-b45c9a79acef"
            },
            {
                "exclude": "ok",
                "record_id": "bu-FC-J-8317",
                "uuid": "89aa7bc2-a562-4a49-84ff-541e939c6152"
            },
            {
                "exclude": "ok",
                "record_id": "bu-FC-J-8318",
                "uuid": "02db119a-44a9-4021-94d9-08939571fd5e"
            },
            {
                "exclude": "ok",
                "record_id": "bu-FC-J-8319",
                "uuid": "65755db4-e347-4b44-91c7-ee830e5e45ec"
            },
            {
                "exclude": "ok",
                "record_id": "bu-FC-J-8320",
                "uuid": "862c27ab-bd5c-4185-9f45-4521eeaed791"
            }
        ],
        "reviewed": true,
        "value": 0.04439136079752539
    },
    "Ar38": {
        "error": 0.001815717868779225,
        "fit": "Bracketing Interpolate",
        "references": [
            {
                "exclude": "ok",
                "record_id": "bu-FC-J-8313",
                "uuid": "0c07543a-f9c1-4862-8dc6-07535ac96d6c"
            },
            {
                "exclude": "ok",
                "record_id": "bu-FC-J-8314",
                "uuid": "6ccaa132-9c86-44a7-91ed-c8fdc767d79e"
            },
            {
                "exclude": "ok",
                "record_id": "bu-FC-J-8315",
                "uuid": "cbcbc245-5469-457a-90b3-fe77b7dc6f25"
            },
            {
                "exclude": "ok",
                "record_id": "bu-FC-J-8316",
                "uuid": "c6ecb00f-17c4-4f29-9960-b45c9a79acef"
            },
            {
                "exclude": "ok",
                "record_id": "bu-FC-J-8317",
                "uuid": "89aa7bc2-a562-4a49-84ff-541e939c6152"
            },
            {
                "exclude": "ok",
                "record_id": "bu-FC-J-8318",
                "uuid": "02db119a-44a9-4021-94d9-08939571fd5e"
            },
            {
                "exclude": "ok",
                "record_id": "bu-FC-J-8319",
                "uuid": "65755db4-e347-4b44-91c7-ee830e5e45ec"
            },
            {
                "exclude": "ok",
                "record_id": "bu-FC-J-8320",
                "uuid": "862c27ab-bd5c-4185-9f45-4521eeaed791"
            }
        ],
        "reviewed": true,
        "value": 0.007181952569421731
    },
    "Ar39": {
        "error": 0.007129815660251408,
        "fit": "Bracketing Interpolate",
        "references": [
            {
                "exclude": "ok",
                "record_id": "bu-FC-J-8313",
                "uuid": "0c07543a-f9c1-4862-8dc6-07535ac96d6c"
            },
            {
                "exclude": "ok",
                "record_id": "bu-FC-J-8314",
                "uuid": "6ccaa132-9c86-44a7-91ed-c8fdc767d79e"
            },
            {
                "exclude": "ok",
                "record_id": "bu-FC-J-8315",
                "uuid": "cbcbc245-5469-457a-90b3-fe77b7dc6f25"
            },
            {
                "exclude": "ok",
                "record_id": "bu-FC-J-8316",
                "uuid": "c6ecb00f-17c4-4f29-9960-b45c9a79acef"
            },
            {
                "exclude": "ok",
                "record_id": "bu-FC-J-8317",
                "uuid": "89aa7bc2-a562-4a49-84ff-541e939c6152"
            },
            {
                "exclude": "ok",
                "record_id": "bu-FC-J-8318",
                "uuid": "02db119a-44a9-4021-94d9-08939571fd5e"
            },
            {
                "exclude": "ok",
                "record_id": "bu-FC-J-8319",
                "uuid": "65755db4-e347-4b44-91c7-ee830e5e45ec"
            },
            {
                "exclude": "ok",
                "record_id": "bu-FC-J-8320",
                "uuid": "862c27ab-bd5c-4185-9f45-4521eeaed791"
            }
        ],
        "reviewed": true,
        "value": -0.0012854187124104275
    },
    "Ar40": {
        "error": 0.005919786652723254,
        "fit": "Bracketing Interpolate",
        "references": [
            {
                "exclude": "ok",
                "record_id": "bu-FC-J-8313",
                "uuid": "0c07543a-f9c1-4862-8dc6-07535ac96d6c"
            },
            {
                "exclude": "ok",
                "record_id": "bu-FC-J-8314",
                "uuid": "6ccaa132-9c86-44a7-91ed-c8fdc767d79e"
            },
            {
                "exclude": "ok",
                "record_id": "bu-FC-J-8315",
                "uuid": "cbcbc245-5469-457a-90b3-fe77b7dc6f25"
            },
            {
                "exclude": "ok",
                "record_id": "bu-FC-J-8316",
                "uuid": "c6ecb00f-17c4-4f29-9960-b45c9a79acef"
            },
            {
                "exclude": "ok",
                "record_id": "bu-FC-J-8317",
                "uuid": "89aa7bc2-a562-4a49-84ff-541e939c6152"
            },
            {
                "exclude": "ok",
                "record_id": "bu-FC-J-8318",
                "uuid": "02db119a-44a9-4021-94d9-08939571fd5e"
            },
            {
                "exclude": "ok",
                "record_id": "bu-FC-J-8319",
                "uuid": "65755db4-e347-4b44-91c7-ee830e5e45ec"
            },
            {
                "exclude": "ok",
                "record_id": "bu-FC-J-8320",
                "uuid": "862c27ab-bd5c-4185-9f45-4521eeaed791"
            }
        ],
        "reviewed": true,
        "value": 0.5477436968043363
    },
    "Ar41": {
        "error": 0.003471753208067266,
        "fit": "previous",
        "references": [
            {
                "exclude": false,
                "record_id": "ba-01-J-2755"
            }
        ],
        "value": 0.017609180778609443
    }
}