{
    "AX": {
        "error": 0.010081054964961833,
        "error_type": "SEM",
        "filter_outliers_dict": {
            "filter_outliers": true,
            "iterations": 1,
            "std_devs": 3,
            "use_iqr_filtering": false,
            "use_standard_deviation_filtering": false
        },
        "fit": "average",
        "fn": 118,
        "include_baseline_error": false,
        "n": 120,
        "outlier_excluded": [
            92,
            86
        ],
        "reviewed": true,
        "user_excluded": [],
        "value": -0.0796725456316766
    },
    "CDD": {},
    "H1": {
        "error": 0.012599304635579466,
        "error_type": "SEM",
        "filter_outliers_dict": {
            "filter_outliers": true,
            "iterations": 1,
            "std_devs": 3,
            "use_iqr_filtering": false,
            "use_standard_deviation_filtering": false
        },
        "fit": "average",
        "fn": 119,
        "include_baseline_error": false,
        "n": 120,
        "outlier_excluded": [
            61
        ],
        "reviewed": true,
        "user_excluded": [],
        "value": -0.11954618181285895
    },
    "H2": {
        "error": 0.009892946157699985,
        "error_type": "SEM",
        "filter_outliers_dict": {
            "filter_outliers": true,
            "iterations": 1,
            "std_devs": 3,
            "use_iqr_filtering": false,
            "use_standard_deviation_filtering": false
        },
        "fit": "average",
        "fn": 120,
        "include_baseline_error": false,
        "n": 120,
        "outlier_excluded": [],
        "reviewed": true,
        "user_excluded": [],
        "value": -0.13543921110685914
    },
    "L1": {
        "error": 0.011262186056802338,
        "error_type": "SEM",
        "filter_outliers_dict": {
            "filter_outliers": true,
            "iterations": 1,
            "std_devs": 3,
            "use_iqr_filtering": false,
            "use_standard_deviation_filtering": false
        },
        "fit": "average",
        "fn": 119,
        "include_baseline_error": false,
        "n": 120,
        "outlier_excluded": [
            33
        ],
        "reviewed": true,
        "user_excluded": [],
        "value": -0.08019017353541405
    },
    "L2(CDD)": {
        "error": 5.717034976143628e-06,
        "fit": "average",
        "value": 2.419261452027882e-05
    }
}