{
    "AX": {
        "error": 0.012435891301749002, 
        "fit": "average", 
        "value": -0.09693400615392207
    }, 
    "H1": {
        "error": 0.011505529167269926, 
        "fit": "average", 
        "value": -0.13985778039237035
    }, 
    "H2": {
        "error": 0.01173875738105116, 
        "fit": "average", 
        "value": -0.18765512435975026
    }, 
    "L1": {
        "error": 0.011954798508833514, 
        "fit": "average", 
        "value": -0.06779353449215188
    }, 
    "L2(CDD)": {
        "error": 7.3442673414332855e-06, 
        "fit": "average", 
        "value": 3.947216061744905e-05
    }
}