{
    "AX": {
        "error": 0.004480237581100524, 
        "filter_outliers_dict": {
            "filter_outliers": true, 
            "iterations": 1, 
            "std_devs": 2
        }, 
        "fit": "average", 
        "value": -0.06638725231138816
    }, 
    "CDD": {
        "error": 4.844817144668337e-06, 
        "filter_outliers_dict": {
            "filter_outliers": true, 
            "iterations": 1, 
            "std_devs": 10
        }, 
        "fit": "average", 
        "value": 1.8608176423866143e-05
    }, 
    "H1": {
        "error": 0.0034896197549278856, 
        "filter_outliers_dict": {
            "filter_outliers": true, 
            "iterations": 1, 
            "std_devs": 2
        }, 
        "fit": "average", 
        "value": -0.031035119501245847
    }, 
    "H2": {
        "error": 0.005819161164764887, 
        "filter_outliers_dict": {
            "filter_outliers": true, 
            "iterations": 1, 
            "std_devs": 2
        }, 
        "fit": "average", 
        "value": -0.19649839147097564
    }, 
    "L1": {
        "error": 0.00206370832574175, 
        "filter_outliers_dict": {
            "filter_outliers": true, 
            "iterations": 1, 
            "std_devs": 2
        }, 
        "fit": "average", 
        "value": -0.021062106214983393
    }, 
    "L2": {
        "error": 0.0038482036373850034, 
        "filter_outliers_dict": {
            "filter_outliers": true, 
            "iterations": 1, 
            "std_devs": 2
        }, 
        "fit": "average", 
        "value": -0.02500530326697308
    }
}