{
    "Ar36": {
        "error": 0.0006810366911681378, 
        "filter_outliers_dict": {
            "filter_outliers": true, 
            "iterations": 2, 
            "std_devs": 2
        }, 
        "fit": "Parabolic", 
        "value": 0.11401107922575579
    }, 
    "Ar37": {
        "error": 0.01140334483244714, 
        "filter_outliers_dict": {
            "filter_outliers": true, 
            "iterations": 2, 
            "std_devs": 2
        }, 
        "fit": "linear", 
        "value": -0.17649184967719694
    }, 
    "Ar38": {
        "error": 0.01217191384311819, 
        "filter_outliers_dict": {
            "filter_outliers": true, 
            "iterations": 2, 
            "std_devs": 2
        }, 
        "fit": "linear", 
        "value": -0.051497611947265064
    }, 
    "Ar39": {
        "error": 0.022722793618195652, 
        "filter_outliers_dict": {
            "filter_outliers": true, 
            "iterations": 2, 
            "std_devs": 2
        }, 
        "fit": "Parabolic", 
        "value": 3.2383111309872135
    }, 
    "Ar40": {
        "error": 0.02174034992384584, 
        "filter_outliers_dict": {
            "filter_outliers": true, 
            "iterations": 2, 
            "std_devs": 2
        }, 
        "fit": "Parabolic", 
        "value": 55.01700376305158
    }
}