{
    "AX": {
        "error": 0.004982958758089179, 
        "filter_outliers_dict": {
            "filter_outliers": true, 
            "iterations": 1, 
            "std_devs": 2
        }, 
        "fit": "average", 
        "value": -0.06467257073477914
    }, 
    "CDD": {
        "error": 8.39192273388949e-06, 
        "filter_outliers_dict": {
            "filter_outliers": true, 
            "iterations": 1, 
            "std_devs": 10
        }, 
        "fit": "average", 
        "value": 4.8953592357273e-05
    }, 
    "H1": {
        "error": 0.003734366041081786, 
        "filter_outliers_dict": {
            "filter_outliers": true, 
            "iterations": 1, 
            "std_devs": 2
        }, 
        "fit": "average", 
        "value": 0.14405551433234842
    }, 
    "H2": {
        "error": 0.005591445680228399, 
        "filter_outliers_dict": {
            "filter_outliers": true, 
            "iterations": 1, 
            "std_devs": 2
        }, 
        "fit": "average", 
        "value": -0.20045245752329696
    }, 
    "L1": {
        "error": 0.001681907945869019, 
        "filter_outliers_dict": {
            "filter_outliers": true, 
            "iterations": 1, 
            "std_devs": 2
        }, 
        "fit": "average", 
        "value": -0.01802253005642755
    }, 
    "L2": {
        "error": 0.00357003534998374, 
        "filter_outliers_dict": {
            "filter_outliers": true, 
            "iterations": 1, 
            "std_devs": 2
        }, 
        "fit": "average", 
        "value": -0.021188707028728587
    }
}