{
    "AX": {
        "error": 0.00475991179440313, 
        "filter_outliers_dict": {
            "filter_outliers": true, 
            "iterations": 1, 
            "std_devs": 2
        }, 
        "fit": "average", 
        "value": -0.06981724475435079
    }, 
    "CDD": {
        "error": 5.242762120465325e-06, 
        "filter_outliers_dict": {
            "filter_outliers": true, 
            "iterations": 1, 
            "std_devs": 10
        }, 
        "fit": "average", 
        "value": 2.2593965627849184e-05
    }, 
    "H1": {
        "error": 0.003696624656406158, 
        "filter_outliers_dict": {
            "filter_outliers": true, 
            "iterations": 1, 
            "std_devs": 2
        }, 
        "fit": "average", 
        "value": 0.1375527480204829
    }, 
    "H2": {
        "error": 0.004376060979925953, 
        "filter_outliers_dict": {
            "filter_outliers": true, 
            "iterations": 1, 
            "std_devs": 2
        }, 
        "fit": "average", 
        "value": -0.20084375541512506
    }, 
    "L1": {
        "error": 0.0019437502137630855, 
        "filter_outliers_dict": {
            "filter_outliers": true, 
            "iterations": 1, 
            "std_devs": 2
        }, 
        "fit": "average", 
        "value": -0.023578226244597673
    }, 
    "L2": {
        "error": 0.004619758936022383, 
        "filter_outliers_dict": {
            "filter_outliers": true, 
            "iterations": 1, 
            "std_devs": 2
        }, 
        "fit": "average", 
        "value": -0.02638840475514628
    }
}