{
    "AX": {
        "error": 0.005421845352224575, 
        "filter_outliers_dict": {
            "filter_outliers": true, 
            "iterations": 1, 
            "std_devs": 2
        }, 
        "fit": "average", 
        "value": -0.057032896476455555
    }, 
    "CDD": {
        "error": 1.3177498477645821e-05, 
        "filter_outliers_dict": {
            "filter_outliers": true, 
            "iterations": 1, 
            "std_devs": 10
        }, 
        "fit": "average", 
        "value": 9.395190010647363e-05
    }, 
    "H1": {
        "error": 0.005654913813136079, 
        "filter_outliers_dict": {
            "filter_outliers": true, 
            "iterations": 1, 
            "std_devs": 2
        }, 
        "fit": "average", 
        "value": 0.09637542995532868
    }, 
    "H2": {
        "error": 0.004259237806119218, 
        "filter_outliers_dict": {
            "filter_outliers": true, 
            "iterations": 1, 
            "std_devs": 2
        }, 
        "fit": "average", 
        "value": -0.08433579666705636
    }, 
    "L1": {
        "error": 0.002886667317769419, 
        "filter_outliers_dict": {
            "filter_outliers": true, 
            "iterations": 1, 
            "std_devs": 2
        }, 
        "fit": "average", 
        "value": -0.031498266189447725
    }, 
    "L2": {
        "error": 0.005997890182975959, 
        "filter_outliers_dict": {
            "filter_outliers": true, 
            "iterations": 1, 
            "std_devs": 2
        }, 
        "fit": "average", 
        "value": -0.024080784165067634
    }
}