{
    "AX": {
        "error": 0.005705387701945232, 
        "filter_outliers_dict": {
            "filter_outliers": true, 
            "iterations": 1, 
            "std_devs": 2
        }, 
        "fit": "average", 
        "value": -0.013353164091432496
    }, 
    "CDD": {
        "error": 1.4989097196439575e-05, 
        "filter_outliers_dict": {
            "filter_outliers": true, 
            "iterations": 1, 
            "std_devs": 10
        }, 
        "fit": "average", 
        "value": 0.00017925033717458994
    }, 
    "H1": {
        "error": 0.0035433567827066266, 
        "filter_outliers_dict": {
            "filter_outliers": true, 
            "iterations": 1, 
            "std_devs": 2
        }, 
        "fit": "average", 
        "value": 0.07825624696442592
    }, 
    "H2": {
        "error": 0.00259463581577561, 
        "filter_outliers_dict": {
            "filter_outliers": true, 
            "iterations": 1, 
            "std_devs": 2
        }, 
        "fit": "average", 
        "value": -0.09137029081961934
    }, 
    "L1": {
        "error": 0.0025813062122637116, 
        "filter_outliers_dict": {
            "filter_outliers": true, 
            "iterations": 1, 
            "std_devs": 2
        }, 
        "fit": "average", 
        "value": 0.033630006157160115
    }, 
    "L2": {
        "error": 0.00410213477974687, 
        "filter_outliers_dict": {
            "filter_outliers": true, 
            "iterations": 1, 
            "std_devs": 2
        }, 
        "fit": "average", 
        "value": -0.01248142190681148
    }
}