{
    "AX": {
        "error": 0.0030814461191323505, 
        "filter_outliers_dict": {
            "filter_outliers": true, 
            "iterations": 1, 
            "std_devs": 2
        }, 
        "fit": "average", 
        "value": -0.08042018356136416
    }, 
    "CDD": {
        "error": 2.003661085421222e-06, 
        "filter_outliers_dict": {
            "filter_outliers": true, 
            "iterations": 1, 
            "std_devs": 10
        }, 
        "fit": "average", 
        "value": 7.443270569546456e-06
    }, 
    "H1": {
        "error": 0.008703235222209725, 
        "filter_outliers_dict": {
            "filter_outliers": true, 
            "iterations": 1, 
            "std_devs": 2
        }, 
        "fit": "average", 
        "value": 0.12865946687384186
    }, 
    "H2": {
        "error": 0.0035372146796921558, 
        "filter_outliers_dict": {
            "filter_outliers": true, 
            "iterations": 1, 
            "std_devs": 2
        }, 
        "fit": "average", 
        "value": -0.19898043909504315
    }, 
    "L1": {
        "error": 0.0011725746994762445, 
        "filter_outliers_dict": {
            "filter_outliers": true, 
            "iterations": 1, 
            "std_devs": 2
        }, 
        "fit": "average", 
        "value": -0.02396700394500091
    }, 
    "L2": {
        "error": 0.002637065565187777, 
        "filter_outliers_dict": {
            "filter_outliers": true, 
            "iterations": 1, 
            "std_devs": 2
        }, 
        "fit": "average", 
        "value": -0.02676940596794484
    }
}