{
    "AX": {
        "error": 0.007359378242964209, 
        "filter_outliers_dict": {
            "filter_outliers": false, 
            "iterations": 1, 
            "std_devs": 2
        }, 
        "fit": "average_SEM", 
        "value": -0.06018345682086821
    }, 
    "H1": {
        "error": 0.0046463296745314474, 
        "filter_outliers_dict": {
            "filter_outliers": false, 
            "iterations": 1, 
            "std_devs": 2
        }, 
        "fit": "average_SEM", 
        "value": 0.087440679126599
    }, 
    "L2": {
        "error": 0.005714971682778639, 
        "filter_outliers_dict": {
            "filter_outliers": false, 
            "iterations": 1, 
            "std_devs": 2
        }, 
        "fit": "average_SEM", 
        "value": -0.01183886060855907
    }
}