{
    "Ar36": {
        "error": 0.0003369844632983944, 
        "filter_outliers_dict": {
            "filter_outliers": true, 
            "iterations": 1, 
            "std_devs": 2
        }, 
        "fit": "Parabolic", 
        "value": 0.02733085110231981
    }, 
    "Ar37": {
        "error": 0.005299248015254577, 
        "filter_outliers_dict": {
            "filter_outliers": true, 
            "iterations": 1, 
            "std_devs": 2
        }, 
        "fit": "linear", 
        "value": 0.01833046334723219
    }, 
    "Ar38": {
        "error": 0.002018754782694795, 
        "filter_outliers_dict": {
            "filter_outliers": true, 
            "iterations": 1, 
            "std_devs": 2
        }, 
        "fit": "linear", 
        "value": 0.8201748928747559
    }, 
    "Ar39": {
        "error": 0.013340284692718475, 
        "filter_outliers_dict": {
            "filter_outliers": true, 
            "iterations": 1, 
            "std_devs": 2
        }, 
        "fit": "Parabolic", 
        "value": 64.97083876720737
    }, 
    "Ar40": {
        "error": 0.03323424505418468, 
        "filter_outliers_dict": {
            "filter_outliers": true, 
            "iterations": 1, 
            "std_devs": 2
        }, 
        "fit": "Parabolic", 
        "value": 810.39231721158
    }, 
    "PM41": {
        "error": 0.06266658514514858, 
        "filter_outliers_dict": {
            "filter_outliers": false, 
            "iterations": 1, 
            "std_devs": 2
        }, 
        "fit": "linear", 
        "value": -0.1478204628153379
    }
}