{
    "Ar40AX": {
        "error": 0.24843218020276378, 
        "filter_outliers_dict": {
            "filter_outliers": false, 
            "iterations": 1, 
            "std_devs": 2
        }, 
        "fit": "parabolic", 
        "value": 884.9449170539792
    }, 
    "Ar40H1": {
        "error": 15.032083771501316, 
        "filter_outliers_dict": {
            "filter_outliers": false, 
            "iterations": 1, 
            "std_devs": 2
        }, 
        "fit": "parabolic", 
        "value": 870.7909866629831
    }, 
    "Ar40L2": {
        "error": 0.46998671023813776, 
        "filter_outliers_dict": {
            "filter_outliers": false, 
            "iterations": 1, 
            "std_devs": 2
        }, 
        "fit": "parabolic", 
        "value": 897.7262478775997
    }
}