{
    "Ar36": {
        "error": 0.00027467498694491136, 
        "filter_outliers_dict": {
            "filter_outliers": true, 
            "iterations": 1, 
            "std_devs": 2
        }, 
        "fit": "Parabolic", 
        "value": 0.019203198571169755
    }, 
    "Ar37": {
        "error": 0.004848711498063788, 
        "filter_outliers_dict": {
            "filter_outliers": true, 
            "iterations": 1, 
            "std_devs": 2
        }, 
        "fit": "linear", 
        "value": 0.020235597203793677
    }, 
    "Ar38": {
        "error": 0.002194312375267674, 
        "filter_outliers_dict": {
            "filter_outliers": true, 
            "iterations": 1, 
            "std_devs": 2
        }, 
        "fit": "linear", 
        "value": -0.0162261624435907
    }, 
    "Ar39": {
        "error": 0.00935964656592853, 
        "filter_outliers_dict": {
            "filter_outliers": true, 
            "iterations": 1, 
            "std_devs": 2
        }, 
        "fit": "Parabolic", 
        "value": -0.071150806528502
    }, 
    "Ar40": {
        "error": 0.007654083096657066, 
        "filter_outliers_dict": {
            "filter_outliers": true, 
            "iterations": 1, 
            "std_devs": 2
        }, 
        "fit": "Parabolic", 
        "value": 4.522791351486102
    }, 
    "PM41": {
        "error": 0.06216154289985728, 
        "filter_outliers_dict": {
            "filter_outliers": false, 
            "iterations": 1, 
            "std_devs": 2
        }, 
        "fit": "linear", 
        "value": -0.18285331917685815
    }
}