{
    "Ar36": {
        "error": 0.00027507525717094335, 
        "filter_outliers_dict": {
            "filter_outliers": true, 
            "iterations": 1, 
            "std_devs": 2
        }, 
        "fit": "Linear", 
        "value": 0.00863131893137846
    }, 
    "Ar37": {
        "error": 0.01135471165130078, 
        "filter_outliers_dict": {
            "filter_outliers": true, 
            "iterations": 1, 
            "std_devs": 2
        }, 
        "fit": "linear", 
        "value": 0.8684824649661838
    }, 
    "Ar38": {
        "error": 0.005150915571239687, 
        "filter_outliers_dict": {
            "filter_outliers": true, 
            "iterations": 1, 
            "std_devs": 2
        }, 
        "fit": "linear", 
        "value": 3.322503865108577
    }, 
    "Ar39": {
        "error": 0.027263734585817285, 
        "filter_outliers_dict": {
            "filter_outliers": true, 
            "iterations": 1, 
            "std_devs": 2
        }, 
        "fit": "Linear", 
        "value": 257.21763789873455
    }, 
    "Ar40": {
        "error": 0.059131420502118795, 
        "filter_outliers_dict": {
            "filter_outliers": true, 
            "iterations": 1, 
            "std_devs": 2
        }, 
        "fit": "Linear", 
        "value": 1440.6030616331645
    }, 
    "PM41": {
        "error": 0.05841446076638564, 
        "filter_outliers_dict": {
            "filter_outliers": false, 
            "iterations": 1, 
            "std_devs": 2
        }, 
        "fit": "linear", 
        "value": -0.1319824829681452
    }
}